[
    {
        "message": "それでも、ここで立ちつくしていたところで、疲れが回復するわけでもない。無理矢理に足を前へ出して、歩き始める。"
    },
    {
        "message": "真っ直ぐに歩こうとしても、よろよろとふらついてしまう。結局、そのまま廊下の壁にもたれかかることになった。"
    },
    {
        "name": "流",
        "message": "はぁ……まぁ、いいか。このまま壁伝いに進もうか……"
    },
    {
        "name": "無限",
        "message": "本当に、良いのですか？"
    },
    {
        "name": "音子",
        "message": "はい、忘れていても支障はありませんから。"
    },
    {
        "name": "流",
        "message": "……ん？"
    },
    {
        "message": "すぐ側のドアが、締まりきっていない。無限の部屋のようだけれど……"
    },
    {
        "message": "部屋の中では無限と音子が二人向かい合い、無限が音子に対して何かしているようだった。"
    },
    {
        "message": "無限が差し出した指先と音子の額のちょうど間あたりで、魔術の光が揺らめいている。"
    },
    {
        "name": "音子",
        "message": "それに……思い出してしまったら、どんな顔をしていればいいか、わかりませんから。特に、あいつの前では……"
    },
    {
        "name": "無限",
        "message": "忘れていても、時はやってきますわよ？それに、未来が確定していない世界では、運命も変わるものですから。"
    },
    {
        "name": "音子",
        "message": "え〜と……な、なんとか忘れたまま運命を変えるってわけには、いきませんか……ね？"
    },
    {
        "name": "無限",
        "message": "くすっ……それは、あなた次第ですわ。"
    },
    {
        "name": "音子",
        "message": "あたし次第……ですか。"
    },
    {
        "name": "無限",
        "message": "私だって万能ではありませんし、なにより人の運命を進んで変質させても、あまり楽しくありませんから。"
    },
    {
        "name": "音子",
        "message": "自分の運命くらい、自分で……ってことですよね。"
    },
    {
        "name": "無限",
        "message": "そうですわね。ただ、忘れておくことがあなたの希望でしたら、それくらいはこうして叶えてあげることは出来ますわよ。"
    },
    {
        "name": "音子",
        "message": "その分は、働けばいいんですよね？"
    },
    {
        "name": "無限",
        "message": "ええ、期待していますわ。あなたの役割を、果たすことを。"
    },
    {
        "name": "音子",
        "message": "それじゃ……お願いします。"
    },
    {
        "name": "無限",
        "message": "……わかりましたわ。"
    },
    {
        "message": "灯っていた魔力の光が音子に近づき、その明るさを増した。無限が、小さく何かを呟いているようだ。"
    },
    {
        "message": "「忘れる」……と、言っていたか？それではあの魔術は、音子の記憶を改めて消そうと……あるいは、封じようとしているのだろうか？"
    },
    {
        "message": "音子の、つらい記憶を……"
    },
    {
        "name": "無限",
        "message": "……あら？流さんですか？"
    },
    {
        "name": "流",
        "message": "あ……ごめん、覗き見する気はなかったんだけど……"
    },
    {
        "name": "無限",
        "message": "かまいませんわよ。別に、いやらしいことをしていたわけでもなければ、悪事を企んでいたわけでもありませんし。"
    },
    {
        "name": "無限",
        "message": "刺激的な様子を期待していたのでしたら、申し訳ありませんけれど。"
    },
    {
        "name": "流",
        "message": "い、いや、そんなのは期待してなけど……"
    },
    {
        "name": "無限",
        "message": "くすっ……流さんの方は、訓練を終えたんですの？ずいぶんと派手にやられたみたいですけれど。"
    },
    {
        "name": "流",
        "message": "えっ？ああ、まぁね……でも、今日はやり返したし。"
    },
    {
        "name": "無限",
        "message": "期待通りですわ。いいえ、期待以上……明日は出撃ですから、今日はもう休んでくださいね。"
    },
    {
        "name": "流",
        "message": "明日……？"
    },
    {
        "name": "無限",
        "message": "ええ。必要なことは、調べられましたから。……猫沼。"
    },
    {
        "name": "音子",
        "message": "はい。"
    },
    {
        "name": "無限",
        "message": "流さんは歩くのも大変なようですから、お部屋にお連れしてあげてくださいな。"
    },
    {
        "name": "音子",
        "message": "はい、かしこまりました。"
    },
    {
        "name": "無限",
        "message": "十分、休んでくださいね？"
    },
    {
        "name": "流",
        "message": "う、うん……"
    }
]