[
    {
        "index": 1,
        "name": "",
        "pre_jp": "良すぎるほど天気の良い晴れの空の下、大きな砦をぐるりと回るようにしてグリムゲルデと手を繋いで歩いた。",
        "post_jp": "良すぎるほど天気の良い晴れの空の下、大きな砦をぐるりと回るようにしてグリムゲルデと手を繋いで歩いた。",
        "pre_zh": "在天气好得过头的晴朗天空下，我和格里姆格德手牵着手，绕着大堡垒走了一圈。",
        "proofread_zh": "",
        "problem": "词典_钢炎 グリム -> 加尔姆 未使用",
        "trans_by": "sakura-010",
        "proofread_by": "",
        "post_zh_preview": "在天气好得过头的晴朗天空下，我和格里姆格德手牵着手，绕着大堡垒走了一圈。"
    },
    {
        "index": 2,
        "name": "",
        "pre_jp": "グリムゲルデはずっと上機嫌で、繋いだ手を大きく振り回したり、時々思い出したように抱きついてきた。",
        "post_jp": "グリムゲルデはずっと上機嫌で、繋いだ手を大きく振り回したり、時々思い出したように抱きついてきた。",
        "pre_zh": "格里姆格德一直显得很开心，她会大动作地挥舞我们牵着的手，有时还会突然想起什么似的抱住我。",
        "proofread_zh": "",
        "problem": "词典_钢炎 グリム -> 加尔姆 未使用",
        "trans_by": "sakura-010",
        "proofread_by": "",
        "post_zh_preview": "格里姆格德一直显得很开心，她会大动作地挥舞我们牵着的手，有时还会突然想起什么似的抱住我。"
    },
    {
        "index": 3,
        "name": "",
        "pre_jp": "途中で木陰に二人で並んで座り、桜火が作ってくれたお弁当を一緒に食べて……少し、桜火に対して申し訳ないことをしているような気持ちになったが。",
        "post_jp": "途中で木陰に二人で並んで座り、桜火が作ってくれたお弁当を一緒に食べて……少し、桜火に対して申し訳ないことをしているような気持ちになったが。",
        "pre_zh": "我们在途中找了个树荫并排坐下，一起吃着樱火做的便当……虽然我有点觉得对樱火有些过意不去。",
        "proofread_zh": "",
        "trans_by": "sakura-010",
        "proofread_by": "",
        "post_zh_preview": "我们在途中找了个树荫并排坐下，一起吃着樱火做的便当……虽然我有点觉得对樱火有些过意不去。"
    },
    {
        "index": 4,
        "name": "",
        "pre_jp": "グリムゲルデは、食べさせてもらうことが気に入ったらしく、何度もあ〜んと口を開けてせがんできた。",
        "post_jp": "グリムゲルデは、食べさせてもらうことが気に入ったらしく、何度もあ〜んと口を開けてせがんできた。",
        "pre_zh": "格里姆格德似乎很喜欢让我喂她吃东西，她不停地张开嘴，向我索求食物。",
        "proofread_zh": "",
        "problem": "词典_钢炎 グリム -> 加尔姆 未使用",
        "trans_by": "sakura-010",
        "proofread_by": "",
        "post_zh_preview": "格里姆格德似乎很喜欢让我喂她吃东西，她不停地张开嘴，向我索求食物。"
    },
    {
        "index": 5,
        "name": "",
        "pre_jp": "散歩しながら話したことは、他愛のないことばかりだった。",
        "post_jp": "散歩しながら話したことは、他愛のないことばかりだった。",
        "pre_zh": "我们一边散步一边聊天，都是些无关紧要的事情。",
        "proofread_zh": "",
        "trans_by": "sakura-010",
        "proofread_by": "",
        "post_zh_preview": "我们一边散步一边聊天，都是些无关紧要的事情。"
    },
    {
        "index": 6,
        "name": "",
        "pre_jp": "ペットを飼ったことはあるかと聞かれたり、彼女のお気に入りのペット・ガルムはもの凄く大勢いると聞かされたり。",
        "post_jp": "ペットを飼ったことはあるかと聞かれたり、彼女のお気に入りのペット・ガルムはもの凄く大勢いると聞かされたり。",
        "pre_zh": "她问我有没有养过宠物，还告诉我她最喜欢的宠物加姆数量非常庞大。。",
        "proofread_zh": "",
        "trans_by": "sakura-010",
        "proofread_by": "",
        "post_zh_preview": "她问我有没有养过宠物，还告诉我她最喜欢的宠物加姆数量非常庞大。。"
    },
    {
        "index": 7,
        "name": "",
        "pre_jp": "ガルム達は、呼べばすぐに駆けつけてくるとか、普段は放し飼いだから、たまにしかお散歩はしないとか……",
        "post_jp": "ガルム達は、呼べばすぐに駆けつけてくるとか、普段は放し飼いだから、たまにしかお散歩はしないとか……",
        "pre_zh": "加姆们，只要叫一声就会立刻跑过来，平时都是放养的，所以只有偶尔才会去散步……",
        "proofread_zh": "",
        "trans_by": "sakura-010",
        "proofread_by": "",
        "post_zh_preview": "加姆们，只要叫一声就会立刻跑过来，平时都是放养的，所以只有偶尔才会去散步……"
    },
    {
        "index": 8,
        "name": "ガルム",
        "pre_jp": "クンクン、クンッ……ク〜ンク〜ン！",
        "post_jp": "クンクン、クンッ……ク〜ンク〜ン！",
        "pre_zh": "嗅嗅，嗅……嗅～嗅～！",
        "proofread_zh": "",
        "trans_by": "sakura-010",
        "proofread_by": "",
        "post_zh_preview": "嗅嗅，嗅……嗅～嗅～！"
    },
    {
        "index": 9,
        "name": "流",
        "pre_jp": "ちょ、ちょっと！くすぐったいから……！",
        "post_jp": "ちょ、ちょっと！くすぐったいから……！",
        "pre_zh": "等、等一下！这样会痒的……！",
        "proofread_zh": "",
        "trans_by": "sakura-010",
        "proofread_by": "",
        "post_zh_preview": "等、等一下！这样会痒的……！"
    },
    {
        "index": 10,
        "name": "グリムゲルデ",
        "pre_jp": "あはは！すっかり懐かれちゃったね？",
        "post_jp": "あはは！すっかり懐かれちゃったね？",
        "pre_zh": "啊哈哈！你完全被它们喜欢上了呢？",
        "proofread_zh": "",
        "trans_by": "sakura-010",
        "proofread_by": "",
        "post_zh_preview": "啊哈哈！你完全被它们喜欢上了呢？"
    },
    {
        "index": 11,
        "name": "グリムゲルデ",
        "pre_jp": "これからも、ちゃんと流と仲良くするんだよ、ガルム４号？",
        "post_jp": "これからも、ちゃんと流と仲良くするんだよ、ガルム４号？",
        "pre_zh": "从现在开始，也要和流好好相处哦，加姆4号？",
        "proofread_zh": "",
        "trans_by": "sakura-010",
        "proofread_by": "",
        "post_zh_preview": "从现在开始，也要和流好好相处哦，加姆4号？"
    },
    {
        "index": 12,
        "name": "ガルム",
        "pre_jp": "アンッ！",
        "post_jp": "アンッ！",
        "pre_zh": "嗯！",
        "proofread_zh": "",
        "trans_by": "sakura-010",
        "proofread_by": "",
        "post_zh_preview": "嗯！"
    },
    {
        "index": 13,
        "name": "流",
        "pre_jp": "は、ははは……よろしく。",
        "post_jp": "は、ははは……よろしく。",
        "pre_zh": "哈、哈哈哈……请多关照。",
        "proofread_zh": "",
        "trans_by": "sakura-010",
        "proofread_by": "",
        "post_zh_preview": "哈、哈哈哈……请多关照。"
    },
    {
        "index": 14,
        "name": "ガルム",
        "pre_jp": "アウアンッ！",
        "post_jp": "アウアンッ！",
        "pre_zh": "哦呜嗯！",
        "proofread_zh": "",
        "trans_by": "sakura-010",
        "proofread_by": "",
        "post_zh_preview": "哦呜嗯！"
    },
    {
        "index": 15,
        "name": "ヘルムヴィーゲ",
        "pre_jp": "グリムちゃ〜〜〜んっ！",
        "post_jp": "グリムちゃ〜〜〜んっ！",
        "pre_zh": "格里姆酱～～～！",
        "proofread_zh": "",
        "problem": "词典_钢炎 グリム -> 加尔姆 未使用",
        "trans_by": "sakura-010",
        "proofread_by": "",
        "post_zh_preview": "格里姆酱～～～！"
    },
    {
        "index": 16,
        "name": "グリムゲルデ",
        "pre_jp": "うん？あっ、ヘルム！",
        "post_jp": "うん？あっ、ヘルム！",
        "pre_zh": "嗯？啊，赫尔姆！",
        "proofread_zh": "",
        "trans_by": "sakura-010",
        "proofread_by": "",
        "post_zh_preview": "嗯？啊，赫尔姆！"
    },
    {
        "index": 17,
        "name": "ヘルムヴィーゲ",
        "pre_jp": "フレズちゃん、ゆっくりね？ゆっくり降りてね？",
        "post_jp": "フレズちゃん、ゆっくりね？ゆっくり降りてね？",
        "pre_zh": "弗雷兹酱，慢慢来哦？慢慢下来哦？",
        "proofread_zh": "",
        "trans_by": "sakura-010",
        "proofread_by": "",
        "post_zh_preview": "弗雷兹酱，慢慢来哦？慢慢下来哦？"
    },
    {
        "index": 18,
        "name": "フレズベルク",
        "pre_jp": "ぴぅういっ！",
        "post_jp": "ぴぅういっ！",
        "pre_zh": "哔呜呜！",
        "proofread_zh": "",
        "trans_by": "sakura-010",
        "proofread_by": "",
        "post_zh_preview": "哔呜呜！"
    },
    {
        "index": 19,
        "name": "ヘルムヴィーゲ",
        "pre_jp": "交代よ、交代〜♪ヘルムは、ちゃ〜〜んと自分の分を調べてきたんだからぁ。",
        "post_jp": "交代よ、交代〜♪ヘルムは、ちゃ〜〜んと自分の分を調べてきたんだからぁ。",
        "pre_zh": "轮班了，轮班～♪赫尔姆已经好好地调查了自己的份了呢。",
        "proofread_zh": "",
        "trans_by": "sakura-010",
        "proofread_by": "",
        "post_zh_preview": "轮班了，轮班～♪赫尔姆已经好好地调查了自己的份了呢。"
    },
    {
        "index": 20,
        "name": "グリムゲルデ",
        "pre_jp": "ええ〜〜〜っ！？もう！？じゃあ、お散歩で終わりかぁ……",
        "post_jp": "ええ〜〜〜っ！？もう！？じゃあ、お散歩で終わりかぁ……",
        "pre_zh": "啊啊～～～！？已经！？那么，散步就结束了吗……",
        "proofread_zh": "",
        "trans_by": "sakura-010",
        "proofread_by": "",
        "post_zh_preview": "啊啊～～～！？已经！？那么，散步就结束了吗……"
    },
    {
        "index": 21,
        "name": "ヘルムヴィーゲ",
        "pre_jp": "んふふ〜今度はぁ、ヘルムと一緒ですからねぇ？おにゃー様",
        "post_jp": "んふふ〜今度はぁ、ヘルムと一緒ですからねぇ？おなー様",
        "pre_zh": "嗯呼呼～这次是和赫尔姆一起呢？主人",
        "proofread_zh": "",
        "trans_by": "sakura-010",
        "proofread_by": "",
        "post_zh_preview": "嗯呼呼～这次是和赫尔姆一起呢？主人"
    },
    {
        "index": 22,
        "name": "流",
        "pre_jp": "は、はは……わかってるよ。",
        "post_jp": "は、はは……わかってるよ。",
        "pre_zh": "哈、哈哈……我知道了。",
        "proofread_zh": "",
        "trans_by": "sakura-010",
        "proofread_by": "",
        "post_zh_preview": "哈、哈哈……我知道了。"
    },
    {
        "index": 23,
        "name": "グリムゲルデ",
        "pre_jp": "しょうがないなぁ……",
        "post_jp": "しょうがないなぁ……",
        "pre_zh": "没办法了……",
        "proofread_zh": "",
        "trans_by": "sakura-010",
        "proofread_by": "",
        "post_zh_preview": "没办法了……"
    },
    {
        "index": 24,
        "name": "グリムゲルデ",
        "pre_jp": "じゃあ行ってくるから、後はよろしくね？",
        "post_jp": "じゃあ行ってくるから、後はよろしくね？",
        "pre_zh": "那我就去一趟，剩下的就拜托你们了？",
        "proofread_zh": "",
        "trans_by": "sakura-010",
        "proofread_by": "",
        "post_zh_preview": "那我就去一趟，剩下的就拜托你们了？"
    },
    {
        "index": 25,
        "name": "ヘルムヴィーゲ",
        "pre_jp": "は〜い。まかせてぇ♪",
        "post_jp": "は〜い。まかせてぇ♪",
        "pre_zh": "好的～。交给我吧♪",
        "proofread_zh": "",
        "trans_by": "sakura-010",
        "proofread_by": "",
        "post_zh_preview": "好的～。交给我吧♪"
    },
    {
        "index": 26,
        "name": "グリムゲルデ",
        "pre_jp": "行くよ、ガルム４号！",
        "post_jp": "行くよ、ガルム４号！",
        "pre_zh": "走吧，加姆4号！",
        "proofread_zh": "",
        "trans_by": "sakura-010",
        "proofread_by": "",
        "post_zh_preview": "走吧，加姆4号！"
    },
    {
        "index": 27,
        "name": "ガルム",
        "pre_jp": "アゥアウッ！",
        "post_jp": "アゥアウッ！",
        "pre_zh": "啊呜啊呜！",
        "proofread_zh": "",
        "trans_by": "sakura-010",
        "proofread_by": "",
        "post_zh_preview": "啊呜啊呜！"
    },
    {
        "index": 28,
        "name": "ヘルムヴィーゲ",
        "pre_jp": "グリムちゃんとは、ずっとお外にいたんですか？",
        "post_jp": "グリムちゃんとは、ずっとお外にいたんですか？",
        "pre_zh": "格里姆格德一直在外面吗？",
        "proofread_zh": "",
        "problem": "词典_钢炎 グリム -> 加尔姆 未使用",
        "trans_by": "sakura-010",
        "proofread_by": "",
        "post_zh_preview": "格里姆格德一直在外面吗？"
    },
    {
        "index": 29,
        "name": "流",
        "pre_jp": "いや。グリムゲルデが受け持ってる大広間を見せてもらったりしたけど……",
        "post_jp": "いや。グリムゲルデが受け持ってる大広間を見せてもらったりしたけど……",
        "pre_zh": "不，我参观了格里姆格德负责的大厅……",
        "proofread_zh": "",
        "problem": "词典_钢炎 グリム -> 加尔姆 未使用",
        "trans_by": "sakura-010",
        "proofread_by": "",
        "post_zh_preview": "不，我参观了格里姆格德负责的大厅……"
    },
    {
        "index": 30,
        "name": "ヘルムヴィーゲ",
        "pre_jp": "それじゃ、ヘルムのお部屋も見てください！なぁ〜んにもないけど、いつもピカピカにお掃除してるんですよ！",
        "post_jp": "それじゃ、ヘルムのお部屋も見てください！なぁ〜んにもないけど、いつもピカピカにお掃除してるんですよ！",
        "pre_zh": "那么，请你也看看赫尔姆的房间！虽然什么都没有，但我总是把它打扫得干干净净的哦！",
        "proofread_zh": "",
        "trans_by": "sakura-010",
        "proofread_by": "",
        "post_zh_preview": "那么，请你也看看赫尔姆的房间！虽然什么都没有，但我总是把它打扫得干干净净的哦！"
    },
    {
        "index": 31,
        "name": "ヘルムヴィーゲ",
        "pre_jp": "さぁさぁ、こっちです♪いきなりお外で……なんて、ヘルムも恥ずかしいですからぁ",
        "post_jp": "さぁさぁ、こっちです♪いきなりお外で……なんて、ヘルムも恥ずかしいですからぁ",
        "pre_zh": "来来，这边♪突然在户外……这样，赫尔姆也会害羞的",
        "proofread_zh": "",
        "trans_by": "sakura-010",
        "proofread_by": "",
        "post_zh_preview": "来来，这边♪突然在户外……这样，赫尔姆也会害羞的"
    },
    {
        "index": 32,
        "name": "流",
        "pre_jp": "う、うん。ちゃんとついていくから、そんなに引っ張らないで……って、今なんて言った？",
        "post_jp": "う、うん。ちゃんとついていくから、そんなに引っ張らないで……って、今なんて言った？",
        "pre_zh": "嗯，嗯。我会好好跟上的，所以别拉得那么紧……等等，你刚才说了什么？",
        "proofread_zh": "",
        "trans_by": "sakura-010",
        "proofread_by": "",
        "post_zh_preview": "嗯，嗯。我会好好跟上的，所以别拉得那么紧……等等，你刚才说了什么？"
    },
    {
        "index": 33,
        "name": "ヘルムヴィーゲ",
        "pre_jp": "ほらほら、早くぅ！♪",
        "post_jp": "ほらほら、早くぅ！♪",
        "pre_zh": "快点快点，快点！♪",
        "proofread_zh": "",
        "trans_by": "sakura-010",
        "proofread_by": "",
        "post_zh_preview": "快点快点，快点！♪"
    }
]